android_mcp/__init__.py
android_mcp/__main__.py
android_mcp/mobile/__init__.py
android_mcp/mobile/service.py
android_mcp/mobile/views.py
android_mcp/tree/__init__.py
android_mcp/tree/config.py
android_mcp/tree/service.py
android_mcp/tree/utils.py
android_mcp/tree/views.py
android_mcp-0.1.0.dist-info/METADATA
android_mcp-0.1.0.dist-info/WHEEL
android_mcp-0.1.0.dist-info/entry_points.txt
android_mcp-0.1.0.dist-info/licenses/LICENSE
android_mcp-0.1.0.dist-info/RECORD
