Metadata-Version: 2.4
Name: android-mcp
Version: 0.1.0
Summary: Lightweight MCP Server for Android Operating System
Project-URL: Homepage, https://github.com/CursorTouch/Android-MCP
License: MIT License
License-File: LICENSE
Keywords: android,automation,mcp,mobile
Requires-Python: >=3.13
Requires-Dist: fastmcp>=2.14.0
Requires-Dist: ipykernel>=6.30.1
Requires-Dist: pillow>=11.2.1
Requires-Dist: tabulate>=0.9.0
Requires-Dist: uiautomator2>=3.3.1
